mkdocs_bpmn/__init__.py
mkdocs_bpmn/elements.py
mkdocs_bpmn/plugin.py
mkdocs_bpmn-0.1.0rc4.dist-info/METADATA
mkdocs_bpmn-0.1.0rc4.dist-info/WHEEL
mkdocs_bpmn-0.1.0rc4.dist-info/entry_points.txt
mkdocs_bpmn-0.1.0rc4.dist-info/licenses/LICENSE
mkdocs_bpmn-0.1.0rc4.dist-info/RECORD
